datalitex/__init__.py
datalitex-1.0.2.dist-info/LICENCE
datalitex-1.0.2.dist-info/METADATA
datalitex-1.0.2.dist-info/WHEEL
datalitex-1.0.2.dist-info/top_level.txt
datalitex-1.0.2.dist-info/RECORD
